{
	"animations": [
		{
			"offsets": [
				15,
				18
			],
			"loop": false,
			"fps": 24,
			"anim": "hurt",
			"indices": [],
			"name": "BF hit"
		},
		{
			"offsets": [
				-4,
				0
			],
			"loop": true,
			"fps": 24,
			"anim": "scared",
			"indices": [],
			"name": "BF idle shaking"
		},
		{
			"offsets": [
				67,
				72
			],
			"loop": false,
			"fps": 24,
			"anim": "firstDeath",
			"indices": [],
			"name": "BF dies"
		},
		{
			"offsets": [
				67,
				66
			],
			"loop": true,
			"fps": 24,
			"anim": "deathLoop",
			"indices": [],
			"name": "BF Dead Loop"
		},
		{
			"offsets": [
				67,
				130
			],
			"loop": false,
			"fps": 24,
			"anim": "deathConfirm",
			"indices": [],
			"name": "BF Dead confirm"
		},
		{
			"offsets": [
				-110,
				44
			],
			"loop": false,
			"fps": 24,
			"anim": "dodge",
			"indices": [],
			"name": "boyfriend dodge"
		},
		{
			"offsets": [
				294,
				267
			],
			"loop": false,
			"fps": 24,
			"anim": "attack",
			"indices": [],
			"name": "boyfriend attack"
		},
		{
			"offsets": [
				-40,
				-40
			],
			"loop": false,
			"fps": 24,
			"anim": "pre-attack",
			"indices": [],
			"name": "bf pre attack"
		},
		{
			"loop": false,
			"offsets": [
				30,
				102
			],
			"anim": "singDOWN",
			"fps": 14,
			"name": "BF NOTE DOWN0",
			"indices": []
		},
		{
			"loop": false,
			"offsets": [
				31,
				96
			],
			"anim": "singUP",
			"fps": 14,
			"name": "BF NOTE UP0",
			"indices": []
		},
		{
			"loop": false,
			"offsets": [
				36,
				91
			],
			"anim": "idle",
			"fps": 18,
			"name": "BF idle dance",
			"indices": []
		},
		{
			"offsets": [
				25,
				91
			],
			"loop": false,
			"fps": 17,
			"anim": "singDOWNmiss",
			"indices": [],
			"name": "BF NOTE DOWN MISS"
		},
		{
			"offsets": [
				24,
				95
			],
			"loop": false,
			"fps": 18,
			"anim": "singUPmiss",
			"indices": [],
			"name": "BF NOTE UP MISS"
		},
		{
			"loop": false,
			"offsets": [
				47,
				95
			],
			"anim": "hey",
			"fps": 13,
			"name": "BF HEY",
			"indices": []
		},
		{
			"offsets": [
				-28,
				93
			],
			"indices": [],
			"fps": 24,
			"anim": "singRIGHT",
			"loop": false,
			"name": "BF NOTE LEFT0"
		},
		{
			"offsets": [
				-24,
				93
			],
			"indices": [],
			"fps": 15,
			"anim": "singRIGHTmiss",
			"loop": false,
			"name": "BF NOTE LEFT MISS"
		},
		{
			"offsets": [
				85,
				94
			],
			"indices": [],
			"fps": 21,
			"anim": "singLEFTmiss",
			"loop": false,
			"name": "BF NOTE RIGHT MISS"
		},
		{
			"offsets": [
				68,
				94
			],
			"indices": [],
			"fps": 24,
			"anim": "singLEFT",
			"loop": false,
			"name": "BF NOTE RIGHT0"
		}
	],
	"no_antialiasing": true,
	"image": "characters/BOYFRIEND_FNJ",
	"position": [
		-150,
		190
	],
	"healthicon": "bf_sgwlfnf",
	"flip_x": true,
	"healthbar_colors": [
		49,
		183,
		255
	],
	"camera_position": [
		50,
		-90
	],
	"sing_duration": 4,
	"scale": 1
}